councillm/__init__.py
councillm/__main__.py
councillm/cli.py
councillm/config.py
councillm/council.py
councillm/fact_guard.py
councillm/ollama_clnt.py
councillm/runtime.py
councillm/search_tool.py
councillm/utils.py
councillm-1.0.dist-info/licenses/LICENSE
councillm-1.0.dist-info/METADATA
councillm-1.0.dist-info/WHEEL
councillm-1.0.dist-info/entry_points.txt
councillm-1.0.dist-info/top_level.txt
councillm-1.0.dist-info/RECORD
