Metadata-Version: 2.4
Name: councillm
Version: 1.0
Summary: Local LLM Council powered by Ollama
Home-page: https://github.com/Rktim/councillm
Author: Raktim Kalita
Author-email: Raktim Kalita  <raktmxx@gmail.com>
License: LICENSE
Requires-Python: >=3.8
License-File: LICENSE
Requires-Dist: ollama
Requires-Dist: httpx
Requires-Dist: textual
Requires-Dist: ddgs
Dynamic: author
Dynamic: home-page
Dynamic: license-file
Dynamic: requires-python
